docscanner/__init__.py
docscanner/scripts.py
document_scanner_sdk-3.0.0.dist-info/licenses/LICENSE
document_scanner_sdk-3.0.0.dist-info/METADATA
document_scanner_sdk-3.0.0.dist-info/WHEEL
document_scanner_sdk-3.0.0.dist-info/entry_points.txt
document_scanner_sdk-3.0.0.dist-info/top_level.txt
document_scanner_sdk-3.0.0.dist-info/RECORD
